caltha-0.6.data/scripts/caltha
src/__init__.py
caltha-0.6.dist-info/LICENSE.md
caltha-0.6.dist-info/METADATA
caltha-0.6.dist-info/WHEEL
caltha-0.6.dist-info/top_level.txt
caltha-0.6.dist-info/RECORD
