Metadata-Version: 2.1
Name: caltha
Version: 0.6
Summary: A python package to process UMI tagged mixed amplicon                 metabarcoding data.
Home-page: https://github.com/JasperBoom/caltha
Author: Jasper Boom
Author-email: jboom@infernum.nl
License: UNKNOWN
Project-URL: Source, https://github.com/JasperBoom/caltha/tree/master/src
Project-URL: Tracker, https://github.com/JasperBoom/caltha/issues
Project-URL: Documentation, https://jasperboom.github.io/caltha/
Keywords: UMI Metabarcoding Amplicon
Platform: UNKNOWN
Classifier: Development Status :: 4 - Beta
Classifier: License :: OSI Approved :: GNU Affero General Public License v3
Classifier: Natural Language :: English
Classifier: Operating System :: POSIX :: Linux
Classifier: Programming Language :: Python :: 3.8
Classifier: Topic :: Scientific/Engineering :: Bio-Informatics
Requires-Python: >=3.8
Requires-Dist: pandas (>=1.0.5)
Requires-Dist: numpy (>=1.19.0)
Requires-Dist: pyfastx (>=0.6.13)
Requires-Dist: biopython (>=1.77)
